instruction_tool_retrieval-0.1.1.dist-info/licenses/LICENSE
itr/__init__.py
itr/__version__.py
itr/assembly/__init__.py
itr/assembly/prompt_builder.py
itr/cache/__init__.py
itr/cli/__init__.py
itr/cli/main.py
itr/core/__init__.py
itr/core/config.py
itr/core/exceptions.py
itr/core/logging.py
itr/core/types.py
itr/indexing/__init__.py
itr/indexing/chunker.py
itr/indexing/corpus.py
itr/indexing/embedder.py
itr/indexing/sparse_index.py
itr/retrieval/__init__.py
itr/retrieval/dense_retriever.py
itr/retrieval/hybrid_retriever.py
itr/retrieval/sparse_retriever.py
itr/selection/__init__.py
itr/selection/budget_selector.py
instruction_tool_retrieval-0.1.1.dist-info/METADATA
instruction_tool_retrieval-0.1.1.dist-info/WHEEL
instruction_tool_retrieval-0.1.1.dist-info/entry_points.txt
instruction_tool_retrieval-0.1.1.dist-info/top_level.txt
instruction_tool_retrieval-0.1.1.dist-info/RECORD
